wfrmls/__init__.py
wfrmls/adu.py
wfrmls/analytics.py
wfrmls/base_client.py
wfrmls/client.py
wfrmls/data_system.py
wfrmls/deleted.py
wfrmls/exceptions.py
wfrmls/green_verification.py
wfrmls/history.py
wfrmls/lookup.py
wfrmls/media.py
wfrmls/member.py
wfrmls/office.py
wfrmls/openhouse.py
wfrmls/properties.py
wfrmls/property_unit_types.py
wfrmls/py.typed
wfrmls/resource.py
wfrmls-1.3.7.dist-info/licenses/LICENSE
wfrmls-1.3.7.dist-info/METADATA
wfrmls-1.3.7.dist-info/WHEEL
wfrmls-1.3.7.dist-info/top_level.txt
wfrmls-1.3.7.dist-info/RECORD
