Metadata-Version: 2.4
Name: wfrmls
Version: 1.3.7
Summary: Python wrapper for Wasatch Front Regional MLS API
Author-email: WFRMLS API Team <api@utahrealestate.com>
License: MIT License
Project-URL: Homepage, https://github.com/theperrygroup/wfrmls
Project-URL: Documentation, https://theperrygroup.github.io/wfrmls/
Project-URL: Repository, https://github.com/theperrygroup/wfrmls
Project-URL: Issues, https://github.com/theperrygroup/wfrmls/issues
Keywords: wfrmls,mls,real-estate,api,wrapper,reso,utah
Classifier: Development Status :: 4 - Beta
Classifier: Intended Audience :: Developers
Classifier: Operating System :: OS Independent
Classifier: Programming Language :: Python :: 3
Classifier: Programming Language :: Python :: 3.8
Classifier: Programming Language :: Python :: 3.9
Classifier: Programming Language :: Python :: 3.10
Classifier: Programming Language :: Python :: 3.11
Classifier: Programming Language :: Python :: 3.12
Classifier: Topic :: Software Development :: Libraries :: Python Modules
Classifier: Topic :: Office/Business :: Financial :: Investment
Classifier: Typing :: Typed
Requires-Python: >=3.8
License-File: LICENSE
Requires-Dist: requests>=2.25.0
Requires-Dist: python-dotenv>=0.19.0
Provides-Extra: dev
Requires-Dist: pytest>=7.0.0; extra == "dev"
Requires-Dist: pytest-cov>=4.0.0; extra == "dev"
Requires-Dist: pytest-mock>=3.10.0; extra == "dev"
Requires-Dist: responses>=0.23.0; extra == "dev"
Requires-Dist: black>=23.0.0; extra == "dev"
Requires-Dist: flake8>=6.0.0; extra == "dev"
Requires-Dist: mypy>=1.0.0; extra == "dev"
Requires-Dist: isort>=5.12.0; extra == "dev"
Requires-Dist: pylint>=2.17.0; extra == "dev"
Requires-Dist: types-requests>=2.25.0; extra == "dev"
Dynamic: license-file
